odoo/addons/mail_preview_audio/README.rst
odoo/addons/mail_preview_audio/__init__.py
odoo/addons/mail_preview_audio/__manifest__.py
odoo/addons/mail_preview_audio/i18n/mail_preview_audio.pot
odoo/addons/mail_preview_audio/readme/CONTRIBUTORS.rst
odoo/addons/mail_preview_audio/readme/DESCRIPTION.rst
odoo/addons/mail_preview_audio/static/description/icon.png
odoo/addons/mail_preview_audio/static/description/index.html
odoo/addons/mail_preview_audio/static/src/js/preview.js
odoo/addons/mail_preview_audio/static/src/xml/preview.xml
odoo/addons/mail_preview_audio/template/assets.xml
odoo13_addon_mail_preview_audio-13.0.1.0.1.dev6.dist-info/METADATA
odoo13_addon_mail_preview_audio-13.0.1.0.1.dev6.dist-info/WHEEL
odoo13_addon_mail_preview_audio-13.0.1.0.1.dev6.dist-info/top_level.txt
odoo13_addon_mail_preview_audio-13.0.1.0.1.dev6.dist-info/RECORD
